correspondentia/__init__.py
correspondentia/disaggregation.py
correspondentia/input_output.py
correspondentia/matcher.py
correspondentia-0.1.dist-info/LICENSE
correspondentia-0.1.dist-info/METADATA
correspondentia-0.1.dist-info/WHEEL
correspondentia-0.1.dist-info/top_level.txt
correspondentia-0.1.dist-info/RECORD
